datasette_ripgrep/__init__.py
datasette_ripgrep/templates/ripgrep.html
datasette_ripgrep/templates/ripgrep_view_file.html
datasette_ripgrep-0.8.2.dist-info/LICENSE
datasette_ripgrep-0.8.2.dist-info/METADATA
datasette_ripgrep-0.8.2.dist-info/WHEEL
datasette_ripgrep-0.8.2.dist-info/entry_points.txt
datasette_ripgrep-0.8.2.dist-info/top_level.txt
datasette_ripgrep-0.8.2.dist-info/RECORD
