Metadata-Version: 2.1
Name: datasette-ripgrep
Version: 0.8.2
Summary: Web interface for searching your code using ripgrep, built as a Datasette plugin
Home-page: https://github.com/simonw/datasette-ripgrep
Author: Simon Willison
License: Apache License, Version 2.0
Project-URL: Issues, https://github.com/simonw/datasette-ripgrep/issues
Project-URL: CI, https://github.com/simonw/datasette-ripgrep/actions
Project-URL: Changelog, https://github.com/simonw/datasette-ripgrep/releases
Classifier: Framework :: Datasette
Classifier: License :: OSI Approved :: Apache Software License
Requires-Python: >=3.7
License-File: LICENSE
Requires-Dist: datasette
Provides-Extra: test
Requires-Dist: pytest ; extra == 'test'
Requires-Dist: pytest-asyncio ; extra == 'test'
Requires-Dist: httpx ; extra == 'test'
